{
  "code": 200,
  "data": {
    "data": {
      "aac020": "",
      "aaa084": "1",
      "aac001": 9300130258,
      "aae004": "",
      "aae147": "1",
      "prseno": 0,
      "eac149": "",
      "eac001": "6000120378",
      "eac101": "",
      "aac005": "01",
      "aae008": "",
      "aac006": 19860218,
      "aac028": "0",
      "aae007": "",
      "aac003": "毛校军",
      "aae006": "",
      "eab030": "",
      "aac004": "1",
      "aae005": "0571",
      "aac009": "20",
      "aac007": 20180904,
      "aaa029": "1",
      "aae010": "",
      "aac012": "",
      "aae135": "330283198602180016",
      "aac010": "淳安",
      "aae013": "",
      "aac011": "",
      "eab009": "",
      "aaz308": 63355113,
      "aab301": "330127",
      "aab401": "",
      "aac017": "",
      "aac014": "",
      "aac015": "",
      "aae159": ""
    },
    "mainMessage": "ok",
    "messageCode": "0",
    "detailMessage": ""
  },
  "message": "SUCCESS"
}